pylocalize/__init__.py
pylocalize/decorator.py
pylocalize/localize_manager.py
pylocalize-0.1.0.dist-info/LICENSE
pylocalize-0.1.0.dist-info/METADATA
pylocalize-0.1.0.dist-info/WHEEL
pylocalize-0.1.0.dist-info/RECORD
