Metadata-Version: 2.1
Name: pylocalize
Version: 0.1.0
Summary: 
Author: MahmudulHassan5809
Author-email: mahmudul.hassan240@gmail.com
Requires-Python: >=3.12,<4.0
Classifier: Programming Language :: Python :: 3
Classifier: Programming Language :: Python :: 3.12
Classifier: Programming Language :: Python :: 3.13
